MANIFEST.in
README.md
README.rst
setup.cfg
setup.py
saram/__init__.py
saram/saram.py
saram.egg-info/PKG-INFO
saram.egg-info/SOURCES.txt
saram.egg-info/dependency_links.txt
saram.egg-info/entry_points.txt
saram.egg-info/not-zip-safe
saram.egg-info/requires.txt
saram.egg-info/top_level.txt