Metadata-Version: 1.0
Name: saram
Version: 1.0.2
Summary: A library to fetch images from a directory and get OCR and store in txt with orientation rotation check and pdf support.
Home-page: https://github.com/aryaminus/saram
Author: Sunim Acharya
Author-email: sunim.54@gmail.com
License: UNKNOWN
Keywords: ocr,image,pdf
Platform: UNKNOWN
